{"classes":["FIRST NAME","LAST NAME","BIRTH DATE","PHONE","EMAIL","GENDER","SKILLS","LANGUAGES","ADDRESS","DIPLOMA","OTHERS","WORK_EXPERIENCE"],"annotations":[["==============================  \r",{"entities":[]}],["DOUAA LEBLANC  \r",{"entities":[[0,5,"FIRST NAME"],[6,13,"LAST NAME"]]}],["==============================  \r",{"entities":[]}],["Gender: Female  \r",{"entities":[[8,15,"GENDER"]]}],["Professional Title: Executive Chef  \r",{"entities":[]}],["Location: 12 Rue des Saveurs, New Orleans, LA  \r",{"entities":[[10,45,"ADDRESS"]]}],["Phone: +1 (504) 264-0771  \r",{"entities":[[7,24,"PHONE"]]}],["Email: douaa.leblanc.chef@gmail.com  \r",{"entities":[[7,37,"EMAIL"]]}],["Website: www.sophialeblanckitchen.com  \r",{"entities":[]}],["Instagram: @chef.sophia.leblanc  \r",{"entities":[]}],["\r",{"entities":[]}],["==============================  \r",{"entities":[]}],["PROFESSIONAL SUMMARY  \r",{"entities":[]}],["==============================  \r",{"entities":[]}],["Creative and passionate Executive Chef with over 10 years of experience in fine dining and high-volume kitchen environments. Expert in French and Mediterranean cuisine, team leadership, and sustainable sourcing. Known for menu innovation and maintaining top-tier hygiene and safety standards.\r",{"entities":[]}],["\r",{"entities":[]}],["==============================  \r",{"entities":[]}],["CORE SKILLS  \r",{"entities":[]}],["==============================  \r",{"entities":[]}],["• Menu Creation & Innovation  \r",{"entities":[[2,30,"SKILLS"]]}],["• Staff Management & Training  \r",{"entities":[[2,31,"SKILLS"]]}],["• Quality Control & Food Safety  \r",{"entities":[[2,33,"SKILLS"]]}],["• Seasonal & Local Sourcing  \r",{"entities":[[2,29,"SKILLS"]]}],["• Fine Dining Presentation  \r",{"entities":[[2,26,"SKILLS"]]}],["• Budgeting & Inventory Control  \r",{"entities":[]}],["• Event Catering & Tasting Menus  \r",{"entities":[[1,33,"SKILLS"]]}],["\r",{"entities":[]}],["==============================  \r",{"entities":[]}],["WORK HISTORY  \r",{"entities":[]}],["==============================  \r",{"entities":[]}],["\r",{"entities":[]}],["Executive Chef  \r",{"entities":[[0,15,"WORK_EXPERIENCE"]]}],["Le Jardin Gourmet – New Orleans, LA  \r",{"entities":[]}],["2020 – Present  \r",{"entities":[]}],["- Designed a rotating seasonal menu that increased customer retention by 30%.  \r",{"entities":[]}],["- Led a team of 12 chefs and kitchen staff in a Michelin-recommended restaurant.  \r",{"entities":[]}],["- Partnered with local farms for sustainable ingredient sourcing.\r",{"entities":[]}],["\r",{"entities":[]}],["Sous-Chef  \r",{"entities":[[0,10,"WORK_EXPERIENCE"]]}],["Maison Blanche – San Francisco, CA  \r",{"entities":[]}],["2016 – 2020  \r",{"entities":[]}],["- Managed day-to-day kitchen operations and quality control.  \r",{"entities":[]}],["- Supervised plating and ensured consistency across all dishes.  \r",{"entities":[]}],["- Assisted in menu development and staff onboarding.\r",{"entities":[]}],["\r",{"entities":[]}],["Line Cook  \r",{"entities":[[0,10,"WORK_EXPERIENCE"]]}],["Café Provençal – Miami, FL  \r",{"entities":[]}],["2013 – 2016  \r",{"entities":[]}],["- Prepared hot and cold dishes in a fast-paced environment.  \r",{"entities":[]}],["- Specialized in pastries and Mediterranean seafood preparation.  \r",{"entities":[]}],["- Maintained strict hygiene procedures and station organization.\r",{"entities":[]}],["\r",{"entities":[]}],["==============================  \r",{"entities":[]}],["LANGUAGES  \r",{"entities":[]}],["==============================  \r",{"entities":[]}],["• English – Fluent  \r",{"entities":[[2,10,"LANGUAGES"]]}],["• French – Native  \r",{"entities":[[2,8,"LANGUAGES"]]}],["• Italian – Conversational  \r",{"entities":[[2,9,"LANGUAGES"]]}],["\r",{"entities":[]}],["==============================  \r",{"entities":[]}],["AWARDS & RECOGNITION  \r",{"entities":[]}],["==============================  \r",{"entities":[]}],["• Best Chef in Louisiana – Culinary Stars Magazine (2022)  \r",{"entities":[[2,24,"OTHERS"]]}],["• Featured Guest on “MasterKitchen” TV Show – 2021  \r",{"entities":[[1,44,"OTHERS"]]}],["• 2x Gold Medalist – Southern Regional Culinary Challenge  \r",{"entities":[]}],["\r",{"entities":[]}],["==============================  \r",{"entities":[]}],["EDUCATION & TRAINING  \r",{"entities":[]}],["==============================  \r",{"entities":[]}],["Le Cordon Bleu Culinary Institute – Paris, France  \r",{"entities":[]}],["Diploma in Culinary Arts – 2010–2012  \r",{"entities":[[0,24,"DIPLOMA"]]}],["\r",{"entities":[]}],["ServSafe Certified – Valid until 2026  \r",{"entities":[]}],["",{"entities":[]}]]}